[
  {
    "id": "bitcoin",
    "symbol": "btc",
    "name": "Bitcoin",
    "current_price": 73144,
    "market_cap": 1465654562359,
    "market_cap_rank": 1
  },
  {
    "id": "ethereum",
    "symbol": "eth",
    "name": "Ethereum",
    "current_price": 1985.87,
    "market_cap": 239713783252,
    "market_cap_rank": 2
  },
  {
    "id": "tether",
    "symbol": "usdt",
    "name": "Tether",
    "current_price": 0.998216,
    "market_cap": 189246019960,
    "market_cap_rank": 3
  },
  {
    "id": "binancecoin",
    "symbol": "bnb",
    "name": "BNB",
    "current_price": 633.52,
    "market_cap": 85394223366,
    "market_cap_rank": 4
  },
  {
    "id": "ripple",
    "symbol": "xrp",
    "name": "XRP",
    "current_price": 1.29,
    "market_cap": 79680082727,
    "market_cap_rank": 5
  },
  {
    "id": "usd-coin",
    "symbol": "usdc",
    "name": "USDC",
    "current_price": 0.999494,
    "market_cap": 76337073395,
    "market_cap_rank": 6
  },
  {
    "id": "solana",
    "symbol": "sol",
    "name": "Solana",
    "current_price": 80.89,
    "market_cap": 46774624771,
    "market_cap_rank": 7
  },
  {
    "id": "tron",
    "symbol": "trx",
    "name": "TRON",
    "current_price": 0.359844,
    "market_cap": 34115129760,
    "market_cap_rank": 8
  },
  {
    "id": "figure-heloc",
    "symbol": "figr_heloc",
    "name": "Figure Heloc",
    "current_price": 1.035,
    "market_cap": 18775346407,
    "market_cap_rank": 9
  },
  {
    "id": "dogecoin",
    "symbol": "doge",
    "name": "Dogecoin",
    "current_price": 0.098142,
    "market_cap": 15157881677,
    "market_cap_rank": 10
  },
  {
    "id": "hyperliquid",
    "symbol": "hype",
    "name": "Hyperliquid",
    "current_price": 56.7,
    "market_cap": 12641882800,
    "market_cap_rank": 11
  },
  {
    "id": "usds",
    "symbol": "usds",
    "name": "USDS",
    "current_price": 0.999476,
    "market_cap": 11119505964,
    "market_cap_rank": 12
  },
  {
    "id": "leo-token",
    "symbol": "leo",
    "name": "LEO Token",
    "current_price": 10.06,
    "market_cap": 9256478161,
    "market_cap_rank": 13
  },
  {
    "id": "rain",
    "symbol": "rain",
    "name": "Rain",
    "current_price": 0.01426044,
    "market_cap": 8881434725,
    "market_cap_rank": 14
  },
  {
    "id": "zcash",
    "symbol": "zec",
    "name": "Zcash",
    "current_price": 524.44,
    "market_cap": 8761404116,
    "market_cap_rank": 15
  },
  {
    "id": "cardano",
    "symbol": "ada",
    "name": "Cardano",
    "current_price": 0.229857,
    "market_cap": 8503318650,
    "market_cap_rank": 16
  },
  {
    "id": "monero",
    "symbol": "xmr",
    "name": "Monero",
    "current_price": 381.93,
    "market_cap": 7164035952,
    "market_cap_rank": 17
  },
  {
    "id": "bitcoin-cash",
    "symbol": "bch",
    "name": "Bitcoin Cash",
    "current_price": 324.41,
    "market_cap": 6501984839,
    "market_cap_rank": 18
  },
  {
    "id": "chainlink",
    "symbol": "link",
    "name": "Chainlink",
    "current_price": 8.86,
    "market_cap": 6438434221,
    "market_cap_rank": 19
  },
  {
    "id": "whitebit",
    "symbol": "wbt",
    "name": "WhiteBIT Coin",
    "current_price": 53.78,
    "market_cap": 6366662070,
    "market_cap_rank": 20
  },
  {
    "id": "canton-network",
    "symbol": "cc",
    "name": "Canton",
    "current_price": 0.154098,
    "market_cap": 5955470957,
    "market_cap_rank": 21
  },
  {
    "id": "stellar",
    "symbol": "xlm",
    "name": "Stellar",
    "current_price": 0.16801,
    "market_cap": 5624322949,
    "market_cap_rank": 22
  },
  {
    "id": "the-open-network",
    "symbol": "ton",
    "name": "Toncoin",
    "current_price": 1.8,
    "market_cap": 4869467057,
    "market_cap_rank": 23
  },
  {
    "id": "usd1-wlfi",
    "symbol": "usd1",
    "name": "USD1",
    "current_price": 0.997645,
    "market_cap": 4748544821,
    "market_cap_rank": 24
  },
  {
    "id": "ethena-usde",
    "symbol": "usde",
    "name": "Ethena USDe",
    "current_price": 0.998689,
    "market_cap": 4489887124,
    "market_cap_rank": 25
  },
  {
    "id": "dai",
    "symbol": "dai",
    "name": "Dai",
    "current_price": 0.999207,
    "market_cap": 4374825022,
    "market_cap_rank": 26
  },
  {
    "id": "litecoin",
    "symbol": "ltc",
    "name": "Litecoin",
    "current_price": 50.66,
    "market_cap": 3912024517,
    "market_cap_rank": 27
  },
  {
    "id": "memecore",
    "symbol": "m",
    "name": "MemeCore",
    "current_price": 2.97,
    "market_cap": 3879978097,
    "market_cap_rank": 28
  },
  {
    "id": "avalanche-2",
    "symbol": "avax",
    "name": "Avalanche",
    "current_price": 8.8,
    "market_cap": 3800811874,
    "market_cap_rank": 29
  },
  {
    "id": "sui",
    "symbol": "sui",
    "name": "Sui",
    "current_price": 0.9214,
    "market_cap": 3691606036,
    "market_cap_rank": 30
  },
  {
    "id": "hedera-hashgraph",
    "symbol": "hbar",
    "name": "Hedera",
    "current_price": 0.08343,
    "market_cap": 3618137412,
    "market_cap_rank": 31
  },
  {
    "id": "paypal-usd",
    "symbol": "pyusd",
    "name": "PayPal USD",
    "current_price": 0.99974,
    "market_cap": 3235774496,
    "market_cap_rank": 32
  },
  {
    "id": "near",
    "symbol": "near",
    "name": "NEAR Protocol",
    "current_price": 2.41,
    "market_cap": 3119131435,
    "market_cap_rank": 34
  },
  {
    "id": "shiba-inu",
    "symbol": "shib",
    "name": "Shiba Inu",
    "current_price": 0.0000053,
    "market_cap": 3118821033,
    "market_cap_rank": 33
  },
  {
    "id": "hashnote-usyc",
    "symbol": "usyc",
    "name": "Circle USYC",
    "current_price": 1.12,
    "market_cap": 2995497586,
    "market_cap_rank": 35
  },
  {
    "id": "crypto-com-chain",
    "symbol": "cro",
    "name": "Cronos",
    "current_price": 0.06555,
    "market_cap": 2936459858,
    "market_cap_rank": 36
  },
  {
    "id": "global-dollar",
    "symbol": "usdg",
    "name": "Global Dollar",
    "current_price": 0.999646,
    "market_cap": 2670036080,
    "market_cap_rank": 37
  },
  {
    "id": "tether-gold",
    "symbol": "xaut",
    "name": "Tether Gold",
    "current_price": 4383.09,
    "market_cap": 2598514066,
    "market_cap_rank": 38
  },
  {
    "id": "bittensor",
    "symbol": "tao",
    "name": "Bittensor",
    "current_price": 261.08,
    "market_cap": 2505982662,
    "market_cap_rank": 39
  },
  {
    "id": "blackrock-usd-institutional-digital-liquidity-fund",
    "symbol": "buidl",
    "name": "BlackRock USD Institutional Digital Liquidity Fund",
    "current_price": 1,
    "market_cap": 2454787541,
    "market_cap_rank": 40
  },
  {
    "id": "ondo-us-dollar-yield",
    "symbol": "usdy",
    "name": "Ondo US Dollar Yield",
    "current_price": 1.13,
    "market_cap": 2142582864,
    "market_cap_rank": 41
  },
  {
    "id": "mantle",
    "symbol": "mnt",
    "name": "Mantle",
    "current_price": 0.623443,
    "market_cap": 2057832977,
    "market_cap_rank": 42
  },
  {
    "id": "pax-gold",
    "symbol": "paxg",
    "name": "PAX Gold",
    "current_price": 4390.38,
    "market_cap": 2050458674,
    "market_cap_rank": 43
  },
  {
    "id": "polkadot",
    "symbol": "dot",
    "name": "Polkadot",
    "current_price": 1.19,
    "market_cap": 2007629321,
    "market_cap_rank": 44
  },
  {
    "id": "uniswap",
    "symbol": "uni",
    "name": "Uniswap",
    "current_price": 3.02,
    "market_cap": 1918931655,
    "market_cap_rank": 45
  },
  {
    "id": "world-liberty-financial",
    "symbol": "wlfi",
    "name": "World Liberty Financial",
    "current_price": 0.059203,
    "market_cap": 1878573289,
    "market_cap_rank": 46
  },
  {
    "id": "okb",
    "symbol": "okb",
    "name": "OKB",
    "current_price": 85.71,
    "market_cap": 1798796871,
    "market_cap_rank": 47
  },
  {
    "id": "ondo-finance",
    "symbol": "ondo",
    "name": "Ondo",
    "current_price": 0.362193,
    "market_cap": 1765051254,
    "market_cap_rank": 48
  },
  {
    "id": "ripple-usd",
    "symbol": "rlusd",
    "name": "Ripple USD",
    "current_price": 0.999936,
    "market_cap": 1739586118,
    "market_cap_rank": 49
  },
  {
    "id": "htx-dao",
    "symbol": "htx",
    "name": "HTX DAO",
    "current_price": 0.00000189,
    "market_cap": 1716590712,
    "market_cap_rank": 50
  },
  {
    "id": "aster-2",
    "symbol": "aster",
    "name": "Aster",
    "current_price": 0.664016,
    "market_cap": 1713354769,
    "market_cap_rank": 51
  },
  {
    "id": "falcon-finance",
    "symbol": "usdf",
    "name": "Falcon USD",
    "current_price": 0.994498,
    "market_cap": 1663448680,
    "market_cap_rank": 52
  },
  {
    "id": "sky",
    "symbol": "sky",
    "name": "Sky",
    "current_price": 0.065612,
    "market_cap": 1525450645,
    "market_cap_rank": 53
  },
  {
    "id": "pi-network",
    "symbol": "pi",
    "name": "Pi Network",
    "current_price": 0.143792,
    "market_cap": 1524038720,
    "market_cap_rank": 54
  },
  {
    "id": "internet-computer",
    "symbol": "icp",
    "name": "Internet Computer",
    "current_price": 2.66,
    "market_cap": 1471986177,
    "market_cap_rank": 55
  },
  {
    "id": "pepe",
    "symbol": "pepe",
    "name": "Pepe",
    "current_price": 0.00000335,
    "market_cap": 1408075403,
    "market_cap_rank": 56
  },
  {
    "id": "usdd",
    "symbol": "usdd",
    "name": "USDD",
    "current_price": 0.998637,
    "market_cap": 1407767417,
    "market_cap_rank": 57
  },
  {
    "id": "bitget-token",
    "symbol": "bgb",
    "name": "Bitget Token",
    "current_price": 1.99,
    "market_cap": 1396111270,
    "market_cap_rank": 58
  },
  {
    "id": "morpho",
    "symbol": "morpho",
    "name": "Morpho",
    "current_price": 2.09,
    "market_cap": 1327870217,
    "market_cap_rank": 59
  },
  {
    "id": "bfusd",
    "symbol": "bfusd",
    "name": "BFUSD",
    "current_price": 0.997901,
    "market_cap": 1317098319,
    "market_cap_rank": 60
  },
  {
    "id": "ethereum-classic",
    "symbol": "etc",
    "name": "Ethereum Classic",
    "current_price": 8.19,
    "market_cap": 1282206182,
    "market_cap_rank": 61
  },
  {
    "id": "aave",
    "symbol": "aave",
    "name": "Aave",
    "current_price": 80.76,
    "market_cap": 1225690742,
    "market_cap_rank": 62
  },
  {
    "id": "usdtb",
    "symbol": "usdtb",
    "name": "USDtb",
    "current_price": 0.999747,
    "market_cap": 1062719386,
    "market_cap_rank": 63
  },
  {
    "id": "cosmos",
    "symbol": "atom",
    "name": "Cosmos Hub",
    "current_price": 2.07,
    "market_cap": 1055607661,
    "market_cap_rank": 64
  },
  {
    "id": "worldcoin-wld",
    "symbol": "wld",
    "name": "Worldcoin",
    "current_price": 0.308138,
    "market_cap": 1052130624,
    "market_cap_rank": 65
  },
  {
    "id": "kucoin-shares",
    "symbol": "kcs",
    "name": "KuCoin",
    "current_price": 7.74,
    "market_cap": 1042593831,
    "market_cap_rank": 66
  },
  {
    "id": "eutbl",
    "symbol": "eutbl",
    "name": "Spiko EU T-Bills Money Market Fund",
    "current_price": 1.22,
    "market_cap": 1040649057,
    "market_cap_rank": 67
  },
  {
    "id": "render-token",
    "symbol": "render",
    "name": "Render",
    "current_price": 2,
    "market_cap": 1039259534,
    "market_cap_rank": 68
  },
  {
    "id": "united-stables",
    "symbol": "u",
    "name": "United Stables",
    "current_price": 0.999511,
    "market_cap": 1027458314,
    "market_cap_rank": 69
  },
  {
    "id": "quant-network",
    "symbol": "qnt",
    "name": "Quant",
    "current_price": 70.04,
    "market_cap": 1020501835,
    "market_cap_rank": 70
  },
  {
    "id": "blockchain-capital",
    "symbol": "bcap",
    "name": "Blockchain Capital",
    "current_price": 107.16,
    "market_cap": 976453815,
    "market_cap_rank": 71
  },
  {
    "id": "algorand",
    "symbol": "algo",
    "name": "Algorand",
    "current_price": 0.104624,
    "market_cap": 933206544,
    "market_cap_rank": 72
  },
  {
    "id": "polygon-ecosystem-token",
    "symbol": "pol",
    "name": "POL (ex-MATIC)",
    "current_price": 0.087356,
    "market_cap": 930111320,
    "market_cap_rank": 73
  },
  {
    "id": "superstate-short-duration-us-government-securities-fund-ustb",
    "symbol": "ustb",
    "name": "Superstate Short Duration U.S. Government Securities Fund (USTB)",
    "current_price": 11.09,
    "market_cap": 890865475,
    "market_cap_rank": 74
  },
  {
    "id": "janus-henderson-anemoy-treasury-fund",
    "symbol": "jtrsy",
    "name": "Janus Henderson Anemoy Treasury Fund",
    "current_price": 1.1,
    "market_cap": 889582827,
    "market_cap_rank": 75
  },
  {
    "id": "stable-2",
    "symbol": "stable",
    "name": "​​Stable",
    "current_price": 0.03795226,
    "market_cap": 876028921,
    "market_cap_rank": 76
  },
  {
    "id": "kaspa",
    "symbol": "kas",
    "name": "Kaspa",
    "current_price": 0.03110422,
    "market_cap": 852748166,
    "market_cap_rank": 77
  },
  {
    "id": "nexo",
    "symbol": "nexo",
    "name": "NEXO",
    "current_price": 0.814499,
    "market_cap": 814661042,
    "market_cap_rank": 78
  },
  {
    "id": "just",
    "symbol": "jst",
    "name": "JUST",
    "current_price": 0.094259,
    "market_cap": 805122314,
    "market_cap_rank": 79
  },
  {
    "id": "ethena",
    "symbol": "ena",
    "name": "Ethena",
    "current_price": 0.088136,
    "market_cap": 796688486,
    "market_cap_rank": 80
  },
  {
    "id": "dexe",
    "symbol": "dexe",
    "name": "DeXe",
    "current_price": 16.49,
    "market_cap": 770125682,
    "market_cap_rank": 81
  },
  {
    "id": "filecoin",
    "symbol": "fil",
    "name": "Filecoin",
    "current_price": 0.968581,
    "market_cap": 761243926,
    "market_cap_rank": 82
  },
  {
    "id": "aptos",
    "symbol": "apt",
    "name": "Aptos",
    "current_price": 0.911619,
    "market_cap": 747278685,
    "market_cap_rank": 83
  },
  {
    "id": "gatechain-token",
    "symbol": "gt",
    "name": "Gate",
    "current_price": 6.78,
    "market_cap": 722310742,
    "market_cap_rank": 84
  },
  {
    "id": "venice-token",
    "symbol": "vvv",
    "name": "Venice Token",
    "current_price": 15.38,
    "market_cap": 714848946,
    "market_cap_rank": 85
  },
  {
    "id": "flare-networks",
    "symbol": "flr",
    "name": "Flare",
    "current_price": 0.00780894,
    "market_cap": 673989438,
    "market_cap_rank": 86
  },
  {
    "id": "arbitrum",
    "symbol": "arb",
    "name": "Arbitrum",
    "current_price": 0.102676,
    "market_cap": 642328632,
    "market_cap_rank": 87
  },
  {
    "id": "xdce-crowd-sale",
    "symbol": "xdc",
    "name": "XDC Network",
    "current_price": 0.0310278,
    "market_cap": 619024158,
    "market_cap_rank": 88
  },
  {
    "id": "beldex",
    "symbol": "bdx",
    "name": "Beldex",
    "current_price": 0.077688,
    "market_cap": 601096941,
    "market_cap_rank": 89
  },
  {
    "id": "jupiter-exchange-solana",
    "symbol": "jup",
    "name": "Jupiter",
    "current_price": 0.179523,
    "market_cap": 595975336,
    "market_cap_rank": 90
  },
  {
    "id": "pump-fun",
    "symbol": "pump",
    "name": "Pump.fun",
    "current_price": 0.00166847,
    "market_cap": 588350281,
    "market_cap_rank": 91
  },
  {
    "id": "midnight-3",
    "symbol": "night",
    "name": "Midnight",
    "current_price": 0.03520009,
    "market_cap": 584589820,
    "market_cap_rank": 93
  },
  {
    "id": "gho",
    "symbol": "gho",
    "name": "GHO",
    "current_price": 0.998434,
    "market_cap": 583104298,
    "market_cap_rank": 92
  },
  {
    "id": "hash-2",
    "symbol": "hash",
    "name": "Provenance Blockchain",
    "current_price": 0.01044888,
    "market_cap": 559074374,
    "market_cap_rank": 94
  },
  {
    "id": "usual-usd",
    "symbol": "usd0",
    "name": "Usual USD",
    "current_price": 0.998291,
    "market_cap": 553532948,
    "market_cap_rank": 95
  },
  {
    "id": "apxusd",
    "symbol": "apxusd",
    "name": "apxUSD",
    "current_price": 0.999585,
    "market_cap": 541792306,
    "market_cap_rank": 96
  },
  {
    "id": "ousg",
    "symbol": "ousg",
    "name": "OUSG",
    "current_price": 115.38,
    "market_cap": 540535454,
    "market_cap_rank": 97
  },
  {
    "id": "injective-protocol",
    "symbol": "inj",
    "name": "Injective",
    "current_price": 5.4,
    "market_cap": 540302476,
    "market_cap_rank": 98
  },
  {
    "id": "a7a5",
    "symbol": "a7a5",
    "name": "A7A5",
    "current_price": 0.01323697,
    "market_cap": 519055306,
    "market_cap_rank": 100
  },
  {
    "id": "unibase",
    "symbol": "ub",
    "name": "Unibase",
    "current_price": 0.206602,
    "market_cap": 517422963,
    "market_cap_rank": 99
  },
  {
    "id": "vechain",
    "symbol": "vet",
    "name": "VeChain",
    "current_price": 0.00594984,
    "market_cap": 511321802,
    "market_cap_rank": 101
  },
  {
    "id": "ylds",
    "symbol": "ylds",
    "name": "YLDS",
    "current_price": 0.99943,
    "market_cap": 509247505,
    "market_cap_rank": 102
  },
  {
    "id": "fetch-ai",
    "symbol": "fet",
    "name": "Artificial Superintelligence Alliance",
    "current_price": 0.224854,
    "market_cap": 507882763,
    "market_cap_rank": 103
  },
  {
    "id": "dash",
    "symbol": "dash",
    "name": "Dash",
    "current_price": 39.6,
    "market_cap": 503530387,
    "market_cap_rank": 104
  },
  {
    "id": "usx",
    "symbol": "usx",
    "name": "USX",
    "current_price": 0.999276,
    "market_cap": 500766787,
    "market_cap_rank": 105
  },
  {
    "id": "pudgy-penguins",
    "symbol": "pengu",
    "name": "Pudgy Penguins",
    "current_price": 0.00790629,
    "market_cap": 496917452,
    "market_cap_rank": 106
  },
  {
    "id": "true-usd",
    "symbol": "tusd",
    "name": "TrueUSD",
    "current_price": 0.998042,
    "market_cap": 493770854,
    "market_cap_rank": 107
  },
  {
    "id": "edgex",
    "symbol": "edge",
    "name": "edgeX",
    "current_price": 1.39,
    "market_cap": 484899837,
    "market_cap_rank": 108
  },
  {
    "id": "bonk",
    "symbol": "bonk",
    "name": "Bonk",
    "current_price": 0.00000546,
    "market_cap": 480579819,
    "market_cap_rank": 109
  },
  {
    "id": "virtual-protocol",
    "symbol": "virtual",
    "name": "Virtuals Protocol",
    "current_price": 0.714557,
    "market_cap": 469576583,
    "market_cap_rank": 111
  },
  {
    "id": "terra-luna",
    "symbol": "lunc",
    "name": "Terra Luna Classic",
    "current_price": 0.00008428,
    "market_cap": 469344445,
    "market_cap_rank": 110
  },
  {
    "id": "humanity",
    "symbol": "h",
    "name": "Humanity",
    "current_price": 0.256773,
    "market_cap": 467297887,
    "market_cap_rank": 113
  },
  {
    "id": "kite-2",
    "symbol": "kite",
    "name": "Kite",
    "current_price": 0.204977,
    "market_cap": 466125807,
    "market_cap_rank": 112
  },
  {
    "id": "sei-network",
    "symbol": "sei",
    "name": "Sei",
    "current_price": 0.068198,
    "market_cap": 459259037,
    "market_cap_rank": 114
  },
  {
    "id": "official-trump",
    "symbol": "trump",
    "name": "Official Trump",
    "current_price": 1.88,
    "market_cap": 445639423,
    "market_cap_rank": 115
  },
  {
    "id": "spiko-amundi-overnight-swap-fund-eur",
    "symbol": "eursafo",
    "name": "Spiko Amundi Overnight Swap Fund (EUR)",
    "current_price": 1.17,
    "market_cap": 439944708,
    "market_cap_rank": 116
  },
  {
    "id": "janus-henderson-anemoy-aaa-clo-fund",
    "symbol": "jaaa",
    "name": "Janus Henderson Anemoy AAA CLO Fund",
    "current_price": 1.036,
    "market_cap": 433385893,
    "market_cap_rank": 117
  },
  {
    "id": "pancakeswap-token",
    "symbol": "cake",
    "name": "PancakeSwap",
    "current_price": 1.33,
    "market_cap": 432661174,
    "market_cap_rank": 118
  },
  {
    "id": "bianrensheng",
    "symbol": "币安人生",
    "name": "币安人生 (BinanceLife)",
    "current_price": 0.431984,
    "market_cap": 430660433,
    "market_cap_rank": 119
  },
  {
    "id": "euro-coin",
    "symbol": "eurc",
    "name": "EURC",
    "current_price": 1.16,
    "market_cap": 428417127,
    "market_cap_rank": 120
  },
  {
    "id": "blockstack",
    "symbol": "stx",
    "name": "Stacks",
    "current_price": 0.226721,
    "market_cap": 417368285,
    "market_cap_rank": 121
  },
  {
    "id": "adi-token",
    "symbol": "adi",
    "name": "ADI",
    "current_price": 3.78,
    "market_cap": 393554277,
    "market_cap_rank": 122
  },
  {
    "id": "celestia",
    "symbol": "tia",
    "name": "Celestia",
    "current_price": 0.418342,
    "market_cap": 385700625,
    "market_cap_rank": 123
  },
  {
    "id": "aerodrome-finance",
    "symbol": "aero",
    "name": "Aerodrome Finance",
    "current_price": 0.402706,
    "market_cap": 379854219,
    "market_cap_rank": 124
  },
  {
    "id": "first-digital-usd",
    "symbol": "fdusd",
    "name": "First Digital USD",
    "current_price": 0.997009,
    "market_cap": 369160550,
    "market_cap_rank": 125
  },
  {
    "id": "sun-token",
    "symbol": "sun",
    "name": "Sun Token",
    "current_price": 0.0189819,
    "market_cap": 364903119,
    "market_cap_rank": 126
  },
  {
    "id": "chiliz",
    "symbol": "chz",
    "name": "Chiliz",
    "current_price": 0.03369326,
    "market_cap": 349749285,
    "market_cap_rank": 127
  },
  {
    "id": "lab",
    "symbol": "lab",
    "name": "LAB",
    "current_price": 4.49,
    "market_cap": 343309944,
    "market_cap_rank": 128
  },
  {
    "id": "kinesis-gold",
    "symbol": "kau",
    "name": "Kinesis Gold",
    "current_price": 143.74,
    "market_cap": 343001541,
    "market_cap_rank": 129
  },
  {
    "id": "siren-2",
    "symbol": "siren",
    "name": "Siren",
    "current_price": 0.466095,
    "market_cap": 338712021,
    "market_cap_rank": 130
  },
  {
    "id": "audiera",
    "symbol": "beat",
    "name": "Audiera",
    "current_price": 1.26,
    "market_cap": 335832429,
    "market_cap_rank": 131
  },
  {
    "id": "tezos",
    "symbol": "xtz",
    "name": "Tezos",
    "current_price": 0.308902,
    "market_cap": 335411716,
    "market_cap_rank": 132
  },
  {
    "id": "usdgo",
    "symbol": "usdgo",
    "name": "USDGO",
    "current_price": 0.999803,
    "market_cap": 333593790,
    "market_cap_rank": 133
  },
  {
    "id": "curve-dao-token",
    "symbol": "crv",
    "name": "Curve DAO",
    "current_price": 0.210709,
    "market_cap": 319984729,
    "market_cap_rank": 134
  },
  {
    "id": "ether-fi",
    "symbol": "ethfi",
    "name": "Ether.fi",
    "current_price": 0.361823,
    "market_cap": 318622470,
    "market_cap_rank": 135
  },
  {
    "id": "bittorrent",
    "symbol": "btt",
    "name": "BitTorrent",
    "current_price": 3.10269e-7,
    "market_cap": 306895776,
    "market_cap_rank": 137
  },
  {
    "id": "doublezero",
    "symbol": "2z",
    "name": "DoubleZero",
    "current_price": 0.088131,
    "market_cap": 306150869,
    "market_cap_rank": 136
  },
  {
    "id": "pyth-network",
    "symbol": "pyth",
    "name": "Pyth Network",
    "current_price": 0.03849564,
    "market_cap": 302801477,
    "market_cap_rank": 138
  },
  {
    "id": "spx6900",
    "symbol": "spx",
    "name": "SPX6900",
    "current_price": 0.320823,
    "market_cap": 298725278,
    "market_cap_rank": 139
  },
  {
    "id": "gnosis",
    "symbol": "gno",
    "name": "Gnosis",
    "current_price": 112.77,
    "market_cap": 297664743,
    "market_cap_rank": 140
  },
  {
    "id": "the9bit",
    "symbol": "9bit",
    "name": "The9bit",
    "current_price": 0.03615987,
    "market_cap": 296405613,
    "market_cap_rank": 141
  },
  {
    "id": "hastra-prime",
    "symbol": "prime",
    "name": "PRIME",
    "current_price": 1.039,
    "market_cap": 293606054,
    "market_cap_rank": 142
  },
  {
    "id": "usdai",
    "symbol": "usdai",
    "name": "USDai",
    "current_price": 0.999533,
    "market_cap": 288997149,
    "market_cap_rank": 143
  },
  {
    "id": "layerzero",
    "symbol": "zro",
    "name": "LayerZero",
    "current_price": 1.13,
    "market_cap": 285647161,
    "market_cap_rank": 145
  },
  {
    "id": "grass",
    "symbol": "grass",
    "name": "Grass",
    "current_price": 0.487123,
    "market_cap": 285056123,
    "market_cap_rank": 144
  },
  {
    "id": "the-graph",
    "symbol": "grt",
    "name": "The Graph",
    "current_price": 0.02636644,
    "market_cap": 284654630,
    "market_cap_rank": 146
  },
  {
    "id": "lighter",
    "symbol": "lit",
    "name": "Lighter",
    "current_price": 1.12,
    "market_cap": 280824238,
    "market_cap_rank": 147
  },
  {
    "id": "bitcoin-cash-sv",
    "symbol": "bsv",
    "name": "Bitcoin SV",
    "current_price": 13.96,
    "market_cap": 279713312,
    "market_cap_rank": 148
  },
  {
    "id": "olympus",
    "symbol": "ohm",
    "name": "Olympus",
    "current_price": 18.61,
    "market_cap": 279303731,
    "market_cap_rank": 149
  },
  {
    "id": "decred",
    "symbol": "dcr",
    "name": "Decred",
    "current_price": 15.9,
    "market_cap": 277270268,
    "market_cap_rank": 150
  },
  {
    "id": "kinesis-silver",
    "symbol": "kag",
    "name": "Kinesis Silver",
    "current_price": 73.11,
    "market_cap": 276147138,
    "market_cap_rank": 151
  },
  {
    "id": "monad",
    "symbol": "mon",
    "name": "Monad",
    "current_price": 0.02334979,
    "market_cap": 275799934,
    "market_cap_rank": 152
  },
  {
    "id": "frax",
    "symbol": "frax",
    "name": "Legacy Frax Dollar",
    "current_price": 0.988853,
    "market_cap": 272774284,
    "market_cap_rank": 153
  },
  {
    "id": "kaia",
    "symbol": "kaia",
    "name": "Kaia",
    "current_price": 0.04658746,
    "market_cap": 272458882,
    "market_cap_rank": 154
  },
  {
    "id": "lido-dao",
    "symbol": "ldo",
    "name": "Lido DAO",
    "current_price": 0.315361,
    "market_cap": 267729420,
    "market_cap_rank": 155
  },
  {
    "id": "apenft",
    "symbol": "nft",
    "name": "AINFT",
    "current_price": 2.69905e-7,
    "market_cap": 267234132,
    "market_cap_rank": 156
  },
  {
    "id": "zebec-network",
    "symbol": "zbcn",
    "name": "Zebec Network",
    "current_price": 0.00270797,
    "market_cap": 265860017,
    "market_cap_rank": 157
  },
  {
    "id": "conflux-token",
    "symbol": "cfx",
    "name": "Conflux",
    "current_price": 0.050919,
    "market_cap": 264237008,
    "market_cap_rank": 158
  },
  {
    "id": "floki",
    "symbol": "floki",
    "name": "FLOKI",
    "current_price": 0.00002734,
    "market_cap": 263915255,
    "market_cap_rank": 159
  },
  {
    "id": "jasmycoin",
    "symbol": "jasmy",
    "name": "JasmyCoin",
    "current_price": 0.00524334,
    "market_cap": 259242351,
    "market_cap_rank": 160
  },
  {
    "id": "pendle",
    "symbol": "pendle",
    "name": "Pendle",
    "current_price": 1.52,
    "market_cap": 258539440,
    "market_cap_rank": 161
  },
  {
    "id": "telcoin",
    "symbol": "tel",
    "name": "Telcoin",
    "current_price": 0.00267534,
    "market_cap": 254304042,
    "market_cap_rank": 162
  },
  {
    "id": "optimism",
    "symbol": "op",
    "name": "Optimism",
    "current_price": 0.117491,
    "market_cap": 252561674,
    "market_cap_rank": 163
  },
  {
    "id": "royal-dollar",
    "symbol": "rusd",
    "name": "Royal Dollar",
    "current_price": 0.999566,
    "market_cap": 249936672,
    "market_cap_rank": 164
  },
  {
    "id": "jito-governance-token",
    "symbol": "jto",
    "name": "Jito",
    "current_price": 0.503677,
    "market_cap": 241483192,
    "market_cap_rank": 165
  },
  {
    "id": "iota",
    "symbol": "iota",
    "name": "IOTA",
    "current_price": 0.054054,
    "market_cap": 241276343,
    "market_cap_rank": 166
  },
  {
    "id": "falcon-finance-ff",
    "symbol": "ff",
    "name": "Falcon Finance",
    "current_price": 0.102648,
    "market_cap": 240566600,
    "market_cap_rank": 167
  },
  {
    "id": "megausd",
    "symbol": "usdm",
    "name": "MegaUSD",
    "current_price": 1,
    "market_cap": 239140764,
    "market_cap_rank": 168
  },
  {
    "id": "ape-and-pepe",
    "symbol": "apepe",
    "name": "Ape and Pepe",
    "current_price": 0.00000114,
    "market_cap": 238730129,
    "market_cap_rank": 169
  },
  {
    "id": "apyusd",
    "symbol": "apyusd",
    "name": "apyUSD",
    "current_price": 1.37,
    "market_cap": 236347107,
    "market_cap_rank": 170
  },
  {
    "id": "crvusd",
    "symbol": "crvusd",
    "name": "crvUSD",
    "current_price": 0.998129,
    "market_cap": 233032005,
    "market_cap_rank": 171
  },
  {
    "id": "ethereum-name-service",
    "symbol": "ens",
    "name": "Ethereum Name Service",
    "current_price": 5.73,
    "market_cap": 231623236,
    "market_cap_rank": 172
  },
  {
    "id": "build-on",
    "symbol": "b",
    "name": "BUILDon",
    "current_price": 0.228981,
    "market_cap": 228893462,
    "market_cap_rank": 173
  },
  {
    "id": "starknet",
    "symbol": "strk",
    "name": "Starknet",
    "current_price": 0.03619963,
    "market_cap": 227763249,
    "market_cap_rank": 174
  },
  {
    "id": "genius-3",
    "symbol": "genius",
    "name": "Genius",
    "current_price": 0.679134,
    "market_cap": 227050878,
    "market_cap_rank": 175
  },
  {
    "id": "ethgas-2",
    "symbol": "gwei",
    "name": "ETHGas",
    "current_price": 0.107015,
    "market_cap": 224147982,
    "market_cap_rank": 176
  },
  {
    "id": "akash-network",
    "symbol": "akt",
    "name": "Akash Network",
    "current_price": 0.758923,
    "market_cap": 221086707,
    "market_cap_rank": 177
  },
  {
    "id": "plasma",
    "symbol": "xpl",
    "name": "Plasma",
    "current_price": 0.083708,
    "market_cap": 220207621,
    "market_cap_rank": 178
  },
  {
    "id": "usda-2",
    "symbol": "usda",
    "name": "USDa",
    "current_price": 0.982532,
    "market_cap": 216824335,
    "market_cap_rank": 179
  },
  {
    "id": "ultima",
    "symbol": "ultima",
    "name": "Ultima",
    "current_price": 2529.88,
    "market_cap": 214211530,
    "market_cap_rank": 180
  },
  {
    "id": "reallink",
    "symbol": "real",
    "name": "RealLink",
    "current_price": 0.065102,
    "market_cap": 212018188,
    "market_cap_rank": 181
  },
  {
    "id": "billions-network",
    "symbol": "bill",
    "name": "Billions Network",
    "current_price": 0.086973,
    "market_cap": 211271523,
    "market_cap_rank": 182
  },
  {
    "id": "tradable-na-rent-financing-platform-sstn",
    "symbol": "pc0000031",
    "name": "Tradable NA Rent Financing Platform SSTN",
    "current_price": 1,
    "market_cap": 202500000,
    "market_cap_rank": 183
  },
  {
    "id": "nexus-4",
    "symbol": "nex",
    "name": "Nexus",
    "current_price": 0.00000332,
    "market_cap": 199354442,
    "market_cap_rank": 184
  },
  {
    "id": "syrup",
    "symbol": "syrup",
    "name": "Maple Finance",
    "current_price": 0.171264,
    "market_cap": 198628471,
    "market_cap_rank": 185
  },
  {
    "id": "re-protocol-reusd",
    "symbol": "reusd",
    "name": "Re Protocol reUSD",
    "current_price": 1.08,
    "market_cap": 196154635,
    "market_cap_rank": 186
  },
  {
    "id": "raydium",
    "symbol": "ray",
    "name": "Raydium",
    "current_price": 0.703295,
    "market_cap": 189170608,
    "market_cap_rank": 187
  },
  {
    "id": "axie-infinity",
    "symbol": "axs",
    "name": "Axie Infinity",
    "current_price": 1.088,
    "market_cap": 188476774,
    "market_cap_rank": 188
  },
  {
    "id": "onyc",
    "symbol": "onyc",
    "name": "OnRe Tokenized Reinsurance",
    "current_price": 1.1,
    "market_cap": 187012484,
    "market_cap_rank": 190
  },
  {
    "id": "neo",
    "symbol": "neo",
    "name": "NEO",
    "current_price": 2.65,
    "market_cap": 186783125,
    "market_cap_rank": 191
  },
  {
    "id": "pieverse",
    "symbol": "pieverse",
    "name": "Pieverse",
    "current_price": 0.691902,
    "market_cap": 186724722,
    "market_cap_rank": 189
  },
  {
    "id": "skyai",
    "symbol": "skyai",
    "name": "SkyAI",
    "current_price": 0.183703,
    "market_cap": 183210362,
    "market_cap_rank": 192
  },
  {
    "id": "trust-wallet-token",
    "symbol": "twt",
    "name": "Trust Wallet",
    "current_price": 0.435515,
    "market_cap": 180547512,
    "market_cap_rank": 193
  },
  {
    "id": "origintrail",
    "symbol": "trac",
    "name": "OriginTrail",
    "current_price": 0.399131,
    "market_cap": 179965701,
    "market_cap_rank": 194
  },
  {
    "id": "theta-token",
    "symbol": "theta",
    "name": "Theta Network",
    "current_price": 0.180047,
    "market_cap": 179947336,
    "market_cap_rank": 195
  },
  {
    "id": "railgun",
    "symbol": "rail",
    "name": "Railgun",
    "current_price": 3.11,
    "market_cap": 178605769,
    "market_cap_rank": 196
  },
  {
    "id": "the-sandbox",
    "symbol": "sand",
    "name": "The Sandbox",
    "current_price": 0.066598,
    "market_cap": 177453574,
    "market_cap_rank": 197
  },
  {
    "id": "dogwifcoin",
    "symbol": "wif",
    "name": "dogwifhat",
    "current_price": 0.177345,
    "market_cap": 177157007,
    "market_cap_rank": 198
  },
  {
    "id": "chain-2",
    "symbol": "xcn",
    "name": "Onyxcoin",
    "current_price": 0.00446821,
    "market_cap": 170823107,
    "market_cap_rank": 199
  },
  {
    "id": "wefi",
    "symbol": "wfi",
    "name": "WeFi",
    "current_price": 2.02,
    "market_cap": 170148346,
    "market_cap_rank": 200
  }
]